fullurl/__init__.py
fullurl/apps.py
fullurl/tests.py
fullurl/templatetags/__init__.py
fullurl/templatetags/fullurl.py
django_fullurl-1.4.dist-info/LICENSE.txt
django_fullurl-1.4.dist-info/METADATA
django_fullurl-1.4.dist-info/WHEEL
django_fullurl-1.4.dist-info/top_level.txt
django_fullurl-1.4.dist-info/RECORD
