Metadata-Version: 2.1
Name: django-fullurl
Version: 1.4
Summary: Adds three template tags to Django: `fullurl`, `fullstatic` and `buildfullurl`. The template tag `fullurl` acts just like `url`, but it always prints absolute URLs with scheme and domain
Home-page: https://github.com/Flimm/django-fullurl
Author: David D Lowe
Author-email: daviddlowe.flimm@gmail.com
License: mit
Project-URL: GitHub, https://github.com/Flimm/django-fullurl
Project-URL: Change log, https://github.com/Flimm/django-fullurl/blob/master/CHANGELOG.rst
Project-URL: Say Thanks!, https://saythanks.io/to/Flimm
Keywords: django
Classifier: Development Status :: 5 - Production/Stable
Classifier: Framework :: Django
Classifier: Framework :: Django :: 1.8
Classifier: Framework :: Django :: 1.9
Classifier: Framework :: Django :: 1.10
Classifier: Framework :: Django :: 1.11
Classifier: Framework :: Django :: 2.0
Classifier: Framework :: Django :: 2.1
Classifier: Framework :: Django :: 2.2
Classifier: Framework :: Django :: 3.0
Classifier: Framework :: Django :: 3.1
Classifier: Framework :: Django :: 3.2
Classifier: Framework :: Django :: 4.0
Classifier: Framework :: Django :: 4.1
Classifier: Programming Language :: Python :: 2
Classifier: Programming Language :: Python :: 2.7
Classifier: Programming Language :: Python :: 3
Classifier: Programming Language :: Python :: 3.3
Classifier: Programming Language :: Python :: 3.4
Classifier: Programming Language :: Python :: 3.5
Classifier: Programming Language :: Python :: 3.6
Classifier: Programming Language :: Python :: 3.7
Classifier: Programming Language :: Python :: 3.8
Classifier: Programming Language :: Python :: 3.9
Classifier: Programming Language :: Python :: 3.10
Classifier: Programming Language :: Python :: 3.11
Classifier: License :: OSI Approved :: MIT License
Requires-Python: >=2.7, !=3.0.*, !=3.1.*, !=3.2.*
License-File: LICENSE.txt
Requires-Dist: Django (>=1.8)
